geometric_kernels/__init__.py
geometric_kernels/_logging.py
geometric_kernels/jax.py
geometric_kernels/tensorflow.py
geometric_kernels/torch.py
geometric_kernels/version.py
geometric_kernels/feature_maps/__init__.py
geometric_kernels/feature_maps/base.py
geometric_kernels/feature_maps/deterministic.py
geometric_kernels/feature_maps/probability_densities.py
geometric_kernels/feature_maps/random_phase.py
geometric_kernels/feature_maps/rejection_sampling.py
geometric_kernels/frontends/__init__.py
geometric_kernels/frontends/gpflow.py
geometric_kernels/frontends/gpjax.py
geometric_kernels/frontends/gpytorch.py
geometric_kernels/kernels/__init__.py
geometric_kernels/kernels/base.py
geometric_kernels/kernels/feature_map.py
geometric_kernels/kernels/hodge_compositional.py
geometric_kernels/kernels/karhunen_loeve.py
geometric_kernels/kernels/matern_kernel.py
geometric_kernels/kernels/matern_kernel_hamming_graph.py
geometric_kernels/kernels/product.py
geometric_kernels/lab_extras/__init__.py
geometric_kernels/lab_extras/extras.py
geometric_kernels/lab_extras/jax/__init__.py
geometric_kernels/lab_extras/jax/extras.py
geometric_kernels/lab_extras/numpy/__init__.py
geometric_kernels/lab_extras/numpy/extras.py
geometric_kernels/lab_extras/numpy/sparse_extras.py
geometric_kernels/lab_extras/tensorflow/__init__.py
geometric_kernels/lab_extras/tensorflow/extras.py
geometric_kernels/lab_extras/torch/__init__.py
geometric_kernels/lab_extras/torch/extras.py
geometric_kernels/resources/__init__.py
geometric_kernels/resources/precomputed_characters.json
geometric_kernels/sampling/__init__.py
geometric_kernels/sampling/samplers.py
geometric_kernels/spaces/__init__.py
geometric_kernels/spaces/base.py
geometric_kernels/spaces/circle.py
geometric_kernels/spaces/eigenfunctions.py
geometric_kernels/spaces/graph.py
geometric_kernels/spaces/graph_edges.py
geometric_kernels/spaces/hamming_graph.py
geometric_kernels/spaces/hyperbolic.py
geometric_kernels/spaces/hypercube_graph.py
geometric_kernels-0.4.1.dist-info/licenses/LICENSE
geometric_kernels-0.4.1.dist-info/WHEEL
geometric_kernels-0.4.1.dist-info/METADATA
geometric_kernels-0.4.1.dist-info/RECORD
