Metadata-Version: 2.4
Name: geometric_kernels
Version: 0.4.1
Summary: A Python Package offering geometric kernels in NumPy, TensorFlow, PyTorch, and Jax.
Keywords: geometric-kernels
Author-email: The GeometricKernels Contributors <geometric-kernels@googlegroups.com>
Requires-Python: >=3.9
Classifier: License :: OSI Approved :: Apache Software License
Classifier: Programming Language :: Python :: 3.9
Classifier: Programming Language :: Python :: 3.10
Classifier: Programming Language :: Python :: 3.11
Classifier: Programming Language :: Python :: 3.12
Classifier: Operating System :: OS Independent
Classifier: Topic :: Scientific/Engineering :: Artificial Intelligence
License-File: LICENSE
Requires-Dist: backends
Requires-Dist: einops
Requires-Dist: geomstats
Requires-Dist: numpy>=2.0
Requires-Dist: opt-einsum
Requires-Dist: plum-dispatch
Requires-Dist: potpourri3d
Requires-Dist: robust_laplacian
Requires-Dist: scipy>=1.3
Requires-Dist: spherical-harmonics-basis
Requires-Dist: sympy~=1.13
Project-URL: Documentation, https://geometric-kernels.github.io/
Project-URL: Source, https://github.com/geometric-kernels/GeometricKernels
